torch_operation_counter/__init__.py
torch_operation_counter/counters.py
torch_operation_counter/ignore_modules.py
torch_operation_counter/operation_counter.py
torch_operation_counter/utils.py
torch_operation_counter-0.3.8.dist-info/METADATA
torch_operation_counter-0.3.8.dist-info/WHEEL
torch_operation_counter-0.3.8.dist-info/top_level.txt
torch_operation_counter-0.3.8.dist-info/RECORD
